nasa/__init__.py
nasa/api.py
nasa/apod.py
nasa/base.py
nasa/earth.py
nasa/maas.py
nasa/patents.py
nasa/sounds.py
nasa/validations.py
nasa_api_wrapper-0.1.6.dist-info/LICENSE.txt
nasa_api_wrapper-0.1.6.dist-info/METADATA
nasa_api_wrapper-0.1.6.dist-info/WHEEL
nasa_api_wrapper-0.1.6.dist-info/top_level.txt
nasa_api_wrapper-0.1.6.dist-info/RECORD
