Metadata-Version: 2.1
Name: nasa-api-wrapper
Version: 0.1.6
Summary: A convenient wrapper for NASA's APIs
Home-page: https://github.com/brendanv/nasa-api
Author: Brendan Viscomi
Author-email: contact@brendanviscomi.com
License: UNKNOWN
Platform: UNKNOWN
Classifier: Development Status :: 3 - Alpha
Classifier: Intended Audience :: Developers
Classifier: Natural Language :: English
Classifier: Environment :: Console
Classifier: Topic :: Utilities
Classifier: License :: OSI Approved :: GNU General Public License v3 (GPLv3)
Requires-Dist: requests (>=2.22.0)
Requires-Dist: Pillow (>=6.2.1)
Requires-Dist: nose (>=1.3.7)
